setup.py
mlkit/__init__.py
mlkit.egg-info/PKG-INFO
mlkit.egg-info/SOURCES.txt
mlkit.egg-info/dependency_links.txt
mlkit.egg-info/top_level.txt