Metadata-Version: 1.0
Name: mlkit
Version: 0.0.1
Summary: Machine Learning Toolkit
Home-page: UNKNOWN
Author: UNKNOWN
Author-email: UNKNOWN
License: MIT
Platform: UNKNOWN
